README.md
setup.py
brynq_sdk_meta4/__init__.py
brynq_sdk_meta4/cost_centers.py
brynq_sdk_meta4/employees.py
brynq_sdk_meta4/jobs.py
brynq_sdk_meta4/meta4.py
brynq_sdk_meta4.egg-info/PKG-INFO
brynq_sdk_meta4.egg-info/SOURCES.txt
brynq_sdk_meta4.egg-info/dependency_links.txt
brynq_sdk_meta4.egg-info/not-zip-safe
brynq_sdk_meta4.egg-info/requires.txt
brynq_sdk_meta4.egg-info/top_level.txt
brynq_sdk_meta4/schemas/__init__.py
brynq_sdk_meta4/schemas/cost_center.py
brynq_sdk_meta4/schemas/employee.py
brynq_sdk_meta4/schemas/job.py
brynq_sdk_meta4/schemas/reference_enums.py