Metadata-Version: 1.0
Name: brynq-sdk-meta4
Version: 1.0.1
Summary: Meta4 wrapper from BrynQ
Home-page: UNKNOWN
Author: BrynQ
Author-email: support@brynq.com
License: BrynQ License
Platform: UNKNOWN
